makeprompt/__init__.py
makeprompt/__main__.py
makeprompt/cli.py
makeprompt/parts/__init__.py
makeprompt/parts/git.py
makeprompt/parts/jobs.py
makeprompt/parts/virtualenv.py
makeprompt/utils/__init__.py
makeprompt/utils/color.py
makeprompt/utils/make_truecolor_palette.py
makeprompt/utils/palette.py
tests/__init__.py
tests/test_utils_color.py
makeprompt-0.3.dist-info/METADATA
makeprompt-0.3.dist-info/WHEEL
makeprompt-0.3.dist-info/entry_points.txt
makeprompt-0.3.dist-info/top_level.txt
makeprompt-0.3.dist-info/RECORD
