Metadata-Version: 2.1
Name: makeprompt
Version: 0.3
Summary: Generate customised shell prompts (for ZSH)
Home-page: https://github.com/rshk/makeprompt
Author: Samuele Santi
Author-email: samuele@samuelesanti.com
License: BSD License
Platform: UNKNOWN
Classifier: License :: OSI Approved :: BSD License
Classifier: Programming Language :: Python :: 3
Classifier: Programming Language :: Python :: 3.5
Classifier: Programming Language :: Python :: 3.6
Classifier: Programming Language :: Python :: 3.7
Classifier: Programming Language :: Python :: 3.8
Classifier: Programming Language :: Python :: 3 :: Only
